{
  "db_name": "PostgreSQL",
  "query": "INSERT INTO ds_collision_tag (group_id, epoch, tag)\n        VALUES ($1, $2, $3), ($1, $2, $4)\n        ON CONFLICT DO NOTHING\n        RETURNING tag",
  "describe": {
    "columns": [
      {
        "ordinal": 0,
        "name": "tag",
        "type_info": "Bytea"
      }
    ],
    "parameters": {
      "Left": [
        "Uuid",
        "Int8",
        "Bytea",
        "Bytea"
      ]
    },
    "nullable": [
      false
    ]
  },
  "hash": "1fc575e719bf078b5310eb8131e7fa52a19192aed6817d7f949e0e35f867fc84"
}
